django_components_bootstrap/__init__.py
django_components_bootstrap/apps.py
django_components_bootstrap/components/bootstrap5/__init__.py
django_components_bootstrap/components/bootstrap5/accordion.py
django_components_bootstrap/components/bootstrap5/alert.py
django_components_bootstrap/components/bootstrap5/badge.py
django_components_bootstrap/components/bootstrap5/breadcrumb.py
django_components_bootstrap/components/bootstrap5/button.py
django_components_bootstrap/components/bootstrap5/button_group.py
django_components_bootstrap/components/bootstrap5/card.py
django_components_bootstrap/components/bootstrap5/carousel.py
django_components_bootstrap/components/bootstrap5/close_button.py
django_components_bootstrap/components/bootstrap5/collapse.py
django_components_bootstrap/components/bootstrap5/dropdown.py
django_components_bootstrap/components/bootstrap5/dropdown_button.py
django_components_bootstrap/components/bootstrap5/figure.py
django_components_bootstrap/components/bootstrap5/form.py
django_components_bootstrap/components/bootstrap5/form_range.py
django_components_bootstrap/components/bootstrap5/image.py
django_components_bootstrap/components/bootstrap5/input_group.py
django_components_bootstrap/components/bootstrap5/layout.py
django_components_bootstrap/components/bootstrap5/list_group.py
django_components_bootstrap/components/bootstrap5/modal.py
django_components_bootstrap/components/bootstrap5/nav.py
django_components_bootstrap/components/bootstrap5/nav_dropdown.py
django_components_bootstrap/components/bootstrap5/navbar.py
django_components_bootstrap/components/bootstrap5/offcanvas.py
django_components_bootstrap/components/bootstrap5/pagination.py
django_components_bootstrap/components/bootstrap5/placeholder.py
django_components_bootstrap/components/bootstrap5/popover.py
django_components_bootstrap/components/bootstrap5/progress.py
django_components_bootstrap/components/bootstrap5/spinner.py
django_components_bootstrap/components/bootstrap5/stack.py
django_components_bootstrap-0.1.0.dist-info/METADATA
django_components_bootstrap-0.1.0.dist-info/WHEEL
django_components_bootstrap-0.1.0.dist-info/licenses/LICENSE
django_components_bootstrap-0.1.0.dist-info/RECORD
