Metadata-Version: 2.4
Name: django-components-bootstrap
Version: 0.1.0
Summary: Bootstrap components for django-components
Author-email: Joey Jurjens <joeyjurjens@gmail.com>
License-File: LICENSE
Keywords: bootstrap,components,django
Classifier: Development Status :: 3 - Alpha
Classifier: Framework :: Django
Classifier: Framework :: Django :: 5.2
Classifier: Intended Audience :: Developers
Classifier: License :: OSI Approved :: MIT License
Classifier: Programming Language :: Python :: 3
Classifier: Programming Language :: Python :: 3.10
Requires-Python: >=3.10
Requires-Dist: django-components
Provides-Extra: dev
Requires-Dist: ruff; extra == 'dev'
